{
    "data_de_atualizacao": "2018-12-07 04:20:00",
    "origem_informacao": "interna",
    "status_receita": null,
    "status": "nao atualizado",
    "logr_NUMERO2_ENR": "",
    "logr_COMPLEMENTO2_ENR": "",
    "fone2_ENR": "",
    "cpf_CNPJ_SOCIO10_ENR": "",
    "logr_TITULO2_ENR": "",
    "cpf_CNPJ_SOCIO9_ENR": "",
    "cidade1_ENR": "SAO PAULO",
    "cidade2_ENR": "",
    "participacao_SOCIO2_ENR": "50",
    "cnae_SECUNDARIO4_DESC_ENR": "",
    "cnae_SECUNDARIO9_DESC_ENR": "",
    "cnae_SECUNDARIO2_ENR": "",
    "cnae_SECUNDARIO6_DESC_ENR": "",
    "participacao_SOCIO4_ENR": "",
    "cpf_CNPJ_SOCIO8_ENR": "",
    "logr_TITULO3_ENR": "",
    "cpf_CNPJ_SOCIO5_ENR": "",
    "participacao_SOCIO1_ENR": "50",
    "cnae_SECUNDARIO8_DESC_ENR": "",
    "nome_RAZAO_SOCIO9_ENR": "",
    "nome_RAZAO_SOCIO3_ENR": "",
    "tipo_SOCIO9_ENR": "",
    "logr_TIPO1_ENR": "R",
    "nome_RAZAO_SOCIO2_ENR": "Lebron James",
    "tipo_SOCIO1_ENR": "",
    "logr_TITULO1_ENR": "",
    "participacao_SOCIO10_ENR": "",
    "cep1_ENR": "05203220",
    "tipo_SOCIO8_ENR": "",
    "participacao_SOCIO7_ENR": "",
    "cpf_CNPJ_SOCIO6_ENR": "",
    "cnae_SECUNDARIO4_ENR": "",
    "nome_RAZAO_SOCIO8_ENR": "",
    "nome_RAZAO_SOCIO4_ENR": "",
    "cnae_SECUNDARIO6_ENR": "",
    "cnae_SECUNDARIO10_DESC_ENR": "",
    "fone1_ENR": "",
    "cnae_SECUNDARIO3_DESC_ENR": "",
    "cep2_ENR": "",
    "natureza_JURIDICA_ENR": "3999",
    "nome_RAZAO_SOCIO10_ENR": "",
    "nome_RAZAO_SOCIO5_ENR": "",
    "logr_TIPO3_ENR": "",
    "cnae_SECUNDARIO9_ENR": "",
    "tipo_SOCIO4_ENR": "",
    "tipo_SOCIO10_ENR": "",
    "logr_COMPLEMENTO1_ENR": "",
    "data_FUNDACAO_ENR": "1994-03-27",
    "participacao_SOCIO3_ENR": "",
    "cnae_SECUNDARIO5_ENR": "",
    "participacao_SOCIO8_ENR": "",
    "nome_FANTASIA_ENR": "",
    "cnae_SECUNDARIO7_ENR": "",
    "tipo_SOCIO5_ENR": "",
    "logr_NUMERO3_ENR": "",
    "nome_RAZAO_SOCIO1_ENR": "James Harden",
    "cnpj_RADICAL": "00000099",
    "nome_RAZAO_SOCIO7_ENR": "",
    "cnae_SECUNDARIO7_DESC_ENR": "",
    "logr_NOME3_ENR": "",
    "bairro2_ENR": "",
    "cnpj_ORDEM": "0001",
    "razao_SOCIAL_ENR": "ASSOC PERUS DE KARATE SHOTOKAN",
    "cpf_CNPJ_SOCIO3_ENR": "",
    "cnae_SECUNDARIO10_ENR": "",
    "nome_RAZAO_SOCIO6_ENR": "",
    "tipo_SOCIO2_ENR": "F",
    "participacao_SOCIO9_ENR": "",
    "uf3_ENR": "",
    "cnae_SECUNDARIO1_DESC_ENR": "",
    "cidade3_ENR": "",
    "tipo_SOCIO3_ENR": "",
    "logr_COMPLEMENTO3_ENR": "",
    "endereco2_ENR": "",
    "cnae_SECUNDARIO8_ENR": "",
    "endereco1_ENR": "R JOAO JOSE DE GODOI 21",
    "bairro1_ENR": "VL FANTON",
    "cnpj_DIGITO": "21",
    "cep3_ENR": "",
    "cnae_SECUNDARIO2_DESC_ENR": "",
    "cnae_DESCRICAO_ENR": "CLUBES SOCIAIS ESPORTIVOS E SIMILARES",
    "cnae_SECUNDARIO5_DESC_ENR": "",
    "cpf_CNPJ_SOCIO1_ENR": "64241283101",
    "participacao_SOCIO5_ENR": "",
    "bairro3_ENR": "",
    "logr_TIPO2_ENR": "",
    "logr_NOME2_ENR": "",
    "cnae_SECUNDARIO1_ENR": "",
    "ddd1_ENR": "",
    "ddd3_ENR": "",
    "cnae_SECUNDARIO3_ENR": "",
    "uf1_ENR": "SP",
    "participacao_SOCIO6_ENR": "",
    "tipo_SOCIO7_ENR": "",
    "fone3_ENR": "",
    "cpf_CNPJ_SOCIO7_ENR": "",
    "ddd2_ENR": "",
    "logr_NOME1_ENR": "JOAO JOSE DE GODOI",
    "tipo_SOCIO6_ENR": "",
    "endereco3_ENR": "",
    "uf2_ENR": "",
    "cpf_CNPJ_SOCIO2_ENR": "41045910414",
    "cnae_ENR": "9312300",
    "natureza_JURIDICA_DESCRICAO_ENR": "ASSOCIACAO PRIVADA",
    "cpf_CNPJ_SOCIO4_ENR": "",
    "logr_NUMERO1_ENR": "21",
    "radical_CPF_CNPJ_SOCIO2_ENR":"",
    "radical_CPF_CNPJ_SOCIO3_ENR":"",
    "radical_CPF_CNPJ_SOCIO4_ENR":"",
    "radical_CPF_CNPJ_SOCIO5_ENR":"",
    "radical_CPF_CNPJ_SOCIO6_ENR":"",
    "radical_CPF_CNPJ_SOCIO7_ENR":"",
    "radical_CPF_CNPJ_SOCIO8_ENR":"",
    "radical_CPF_CNPJ_SOCIO9_ENR":"",
    "radical_CPF_CNPJ_SOCIO10_ENR":""
}